calculadora/__init__.py
nome_do_seu_pacote-0.1.0.dist-info/METADATA
nome_do_seu_pacote-0.1.0.dist-info/WHEEL
nome_do_seu_pacote-0.1.0.dist-info/top_level.txt
nome_do_seu_pacote-0.1.0.dist-info/RECORD
