Metadata-Version: 2.4
Name: nome-do-seu-pacote
Version: 0.1.0
Summary: Uma descrição curta do seu pacote
Author-email: Seu Nome <seu@email.com>
License: MIT
Project-URL: Homepage, https://github.com/usuario/repositorio
Project-URL: Documentation, https://github.com/usuario/repositorio/wiki
Project-URL: Repository, https://github.com/usuario/repositorio
Project-URL: Issues, https://github.com/usuario/repositorio/issues
Classifier: Programming Language :: Python :: 3
Classifier: License :: OSI Approved :: MIT License
Classifier: Operating System :: OS Independent
Requires-Python: >=3.7
